ristikko/__init__.py
ristikko/chern.py
ristikko/geometry.py
ristikko/impurity.py
ristikko/lattice.py
ristikko/system.py
ristikko/utils.py
ristikko/models/__init__.py
ristikko/models/graphene.py
ristikko/models/point.py
ristikko/models/square.py
ristikko/models/triangular.py
ristikko-0.1.0.dist-info/LICENCE.txt
ristikko-0.1.0.dist-info/METADATA
ristikko-0.1.0.dist-info/WHEEL
ristikko-0.1.0.dist-info/top_level.txt
ristikko-0.1.0.dist-info/RECORD
