Metadata-Version: 2.1
Name: ristikko
Version: 0.1.0
Summary: Classes and utils for tight-binding models
Author-email: Dan Crawford <daniel.j.crawford@jyu.fi>
License: GPLv3+
Classifier: Development Status :: 5 - Production/Stable
Classifier: Programming Language :: Python :: 3
Classifier: License :: OSI Approved :: GNU General Public License v3 or later (GPLv3+)
Classifier: Topic :: Scientific/Engineering :: Physics
Requires-Python: <3.14,>=3.11
License-File: LICENCE.txt
Requires-Dist: scipy <1.16,>=1.13
Requires-Dist: numpy <2.3,>=2
Requires-Dist: joblib <1.5,>=1.4
Requires-Dist: keino ==1
Requires-Dist: tqdm
Requires-Dist: pfapack ==1
